[
    {
        "id": 1,
        "name": "Citron",
        "pin": 1111,
        "poef": []
    },
    {
        "id": 2,
        "name": "Dilly Dilly",
        "pin": 1111,
        "poef": []
    },
    {
        "id": 3,
        "name": "Verdekke",
        "pin": 1111,
        "poef": []
    },
    {
        "id": 4,
        "name": "Gerard",
        "pin": 1111,
        "poef": []
    },
    {
        "id": 5,
        "name": "Chris",
        "pin": 1111,
        "poef": []
    },
    {
        "id": 6,
        "name": "Lander",
        "pin": 1111,
        "poef": []
    },
    {
        "id": 7,
        "name": "Plekkie",
        "pin": 1111,
        "poef": []
    },
    {
        "id": 8,
        "name": "Buxus",
        "pin": 1111,
        "poef": []
    },
    {
        "id": 9,
        "name": "Ior",
        "pin": 1111,
        "poef": []
    },
    {
        "id": 10,
        "name": "Gatse",
        "pin": 1111,
        "poef": []
    },
    {
        "id": 11,
        "name": "Balzzz",
        "pin": 1111,
        "poef": []
    },
    {
        "id": 12,
        "name": "Gaetan",
        "pin": 1111,
        "poef": []
    },
    {
        "id": 13,
        "name": "Kobe",
        "pin": 1111,
        "poef": []
    },
    {
        "id": 14,
        "name": "Razzia",
        "pin": 1111,
        "poef": []
    },
    {
        "id": 15,
        "name": "Dieter",
        "pin": 1111,
        "poef": []
    },
    {
        "id": 16,
        "name": "Xander",
        "pin": 1111,
        "poef": []
    }
]